gitcy/__init__.py
gitcy/cli/__init__.py
gitcy/cli/ctd_.py
gitcy/cli/gundo_.py
gitcy/core/__init__.py
gitcy/core/add.py
gitcy/core/commit.py
gitcy/core/push.py
gitcy/core/undo.py
gitcy-1.0.4.dist-info/entry_points.txt
gitcy-1.0.4.dist-info/LICENSE
gitcy-1.0.4.dist-info/METADATA
gitcy-1.0.4.dist-info/WHEEL
gitcy-1.0.4.dist-info/RECORD
