Metadata-Version: 2.1
Name: gitcy
Version: 1.0.4
Summary: Some usefull gitcommands to make life easier :)
Home-page: https://github.com/ahartlba/gitcy
License: MIT
Author: Andreas Hartl-Bachinger
Author-email: andreas.hartl-bachinger@gmx.at
Requires-Python: >=3.8,<4.0
Classifier: License :: OSI Approved :: MIT License
Classifier: Programming Language :: Python :: 3
Classifier: Programming Language :: Python :: 3.8
Classifier: Programming Language :: Python :: 3.9
Classifier: Programming Language :: Python :: 3.10
Classifier: Programming Language :: Python :: 3.11
